unoccupied/__init__.py
unoccupied/main.py
unoccupied/namefinder.py
unoccupied-0.2.2.dist-info/METADATA
unoccupied-0.2.2.dist-info/RECORD
unoccupied-0.2.2.dist-info/WHEEL
unoccupied-0.2.2.dist-info/top_level.txt
