Metadata-Version: 2.1
Name: unoccupied
Version: 0.2.2
Summary: Generate unoccupied name.
Home-page: https://github.com/civalin/unoccupied
Author: visig
Author-email: visig@protonmail.ch
License: MIT
Platform: UNKNOWN
Classifier: Programming Language :: Python :: 3
Classifier: License :: OSI Approved :: MIT License
Classifier: Topic :: Software Development :: Libraries :: Python Modules
Classifier: Topic :: Text Processing
